datafushion/__init__.py
datafushion/args.py
datafushion/handle.py
datafushion/parse_utils.py
datafushion/version.py
datafushion_plugins_python-1.0.7.data/data/README.md
datafushion_plugins_python-1.0.7.dist-info/METADATA
datafushion_plugins_python-1.0.7.dist-info/WHEEL
datafushion_plugins_python-1.0.7.dist-info/entry_points.txt
datafushion_plugins_python-1.0.7.dist-info/top_level.txt
datafushion_plugins_python-1.0.7.dist-info/zip-safe
datafushion_plugins_python-1.0.7.dist-info/RECORD
