Metadata-Version: 2.1
Name: datafushion-plugins-python
Version: 1.0.7
Summary: DataFushion的python算法插件
Home-page: UNKNOWN
Author: 肖林朋
Author-email: 1553990434@qq.com
License: XiaoLinpeng Licence
Platform: any
Requires-Dist: pypmml
